README.txt
setup.py
Products/__init__.py
Products.ldapconnection.egg-info/PKG-INFO
Products.ldapconnection.egg-info/SOURCES.txt
Products.ldapconnection.egg-info/dependency_links.txt
Products.ldapconnection.egg-info/entry_points.txt
Products.ldapconnection.egg-info/namespace_packages.txt
Products.ldapconnection.egg-info/not-zip-safe
Products.ldapconnection.egg-info/paster_plugins.txt
Products.ldapconnection.egg-info/requires.txt
Products.ldapconnection.egg-info/top_level.txt
Products/ldapconnection/__init__.py
Products/ldapconnection/config.py
Products/ldapconnection/configure.zcml
Products/ldapconnection/exceptions.py
Products/ldapconnection/ldap_connection.py
Products/ldapconnection/log.py
Products/ldapconnection/tm.py
Products/ldapconnection/todo.txt
Products/ldapconnection/lib/Shared.py
Products/ldapconnection/lib/__init__.py
Products/ldapconnection/tests/__init__.py
Products/ldapconnection/tests/config.py
Products/ldapconnection/tests/testLDAPConnection.py
Products/ldapconnection/www/addLDAPConnection.zpt
Products/ldapconnection/www/connectionEdit.zpt
Products/ldapconnection/www/connectionSearch.zpt
Products/ldapconnection/www/connectionStatus.zpt
docs/HISTORY.txt
docs/INSTALL.txt
docs/LICENSE.txt