Metadata-Version: 1.0
Name: Products.ldapconnection
Version: 0.1a1
Summary: LDAP connection for Zope
Home-page: http://pypi.python.org/pypi/Products.ldapconnection
Author: Ricardo Alves
Author-email: rsa@eurotux.com
License: GPL
Keywords: zope ldap
Platform: UNKNOWN
Classifier: Framework :: Plone
Classifier: Programming Language :: Python
Classifier: Topic :: Software Development :: Libraries :: Python Modules
